setup.py
dhaval_indian_states_25/__init__.py
dhaval_indian_states_25/asgi.py
dhaval_indian_states_25/settings.py
dhaval_indian_states_25/urls.py
dhaval_indian_states_25/wsgi.py
dhaval_indian_states_25.egg-info/PKG-INFO
dhaval_indian_states_25.egg-info/SOURCES.txt
dhaval_indian_states_25.egg-info/dependency_links.txt
dhaval_indian_states_25.egg-info/requires.txt
dhaval_indian_states_25.egg-info/top_level.txt
dst1/__init__.py
dst1/admin.py
dst1/apps.py
dst1/fields.py
dst1/forms.py
dst1/models.py
dst1/states.py
dst1/tests.py
dst1/views.py
dst1/migrations/__init__.py