Metadata-Version: 2.1
Name: dhaval_indian_states_25
Version: 0.1
Summary: A Django app that provides Indian States choices as a model and form field.
Author: Dhaval
Author-email: dhavalpatil1510@gmail.com
License: MIT
Classifier: Framework :: Django
Classifier: Programming Language :: Python :: 3
Requires-Dist: Django
